annotation/annotate.py
annotation/filters.py
annotation/utils.py
tools/__init__.py
tools/visualize.py
ImgVidObjectsDetector-0.4.1.dist-info/LICENSE
ImgVidObjectsDetector-0.4.1.dist-info/METADATA
ImgVidObjectsDetector-0.4.1.dist-info/WHEEL
ImgVidObjectsDetector-0.4.1.dist-info/entry_points.txt
ImgVidObjectsDetector-0.4.1.dist-info/top_level.txt
ImgVidObjectsDetector-0.4.1.dist-info/RECORD
