Metadata-Version: 2.1
Name: ImgVidObjectsDetector
Version: 0.4.1
Summary: Single class automated annotation tool using OpenCV
Author-email: "Famosa Muyiwa, LearnOpenCV" <nenling19@gmail.com>
License: MIT License
Project-URL: Homepage, https://github.com/bigvisionai/pyOpenAnnotate
Keywords: Annotation,Automated Annotation,OpenCV Annotate,Image Annotation Tool,Single Class Annotation,Simple Annotation,Annotation Python,Dataset labelling,Object detection,Industrial annotation,openannotate,Annotation software,Deep Learning,Contour Analysis,Thresholding OpenCV,Color Segmentation,segmentation mask,Computer Vision,Bounding Box Annotation
Classifier: Development Status :: 3 - Alpha
Classifier: Operating System :: OS Independent
Classifier: License :: OSI Approved :: MIT License
Classifier: Programming Language :: Python
Classifier: Programming Language :: Python :: 3
Requires-Python: >=3.5
License-File: LICENSE
Requires-Dist: opencv-python
Requires-Dist: natsort
